{"type": "FeatureCollection", "licence": "Data \u00a9 OpenStreetMap contributors, ODbL 1.0. https://osm.org/copyright", "features": [{"type": "Feature", "properties": {"Country": "Vietnam", "City": "Can Tho", "Total cases": "1", "Current cases": "1", "Recovered": "0", "Deceased": "0"}, "bbox": [105.2257535, 9.9193877, 105.8454722, 10.3257006], "geometry": {"type": "Point", "coordinates": [105.7809605, 10.0375517]}}]}