{"type": "FeatureCollection", "licence": "Data \u00a9 OpenStreetMap contributors, ODbL 1.0. https://osm.org/copyright", "features": [{"type": "Feature", "properties": {"Country": "Vietnam", "City": "Da Nang", "Total cases": "6", "Current cases": "6", "Recovered": "0", "Deceased": "0"}, "bbox": [108.052, 15.908, 108.372, 16.228], "geometry": {"type": "Point", "coordinates": [108.212, 16.068]}}, {"type": "Feature", "properties": {"Country": "Vietnam", "City": "Da Nang", "Total cases": "6", "Current cases": "6", "Recovered": "0", "Deceased": "0"}, "bbox": [107.8187817, 15.9179546, 108.6563747, 16.3340091], "geometry": {"type": "Point", "coordinates": [108.21887369936111, 16.12599015]}}, {"type": "Feature", "properties": {"Country": "Vietnam", "City": "Da Nang", "Total cases": "6", "Current cases": "6", "Recovered": "0", "Deceased": "0"}, "bbox": [106.6927659, 20.8601143, 106.6928659, 20.8602143], "geometry": {"type": "Point", "coordinates": [106.6928159, 20.8601643]}}, {"type": "Feature", "properties": {"Country": "Vietnam", "City": "Da Nang", "Total cases": "6", "Current cases": "6", "Recovered": "0", "Deceased": "0"}, "bbox": [106.6735056, 20.9146715, 106.6736056, 20.9147715], "geometry": {"type": "Point", "coordinates": [106.6735556, 20.9147215]}}, {"type": "Feature", "properties": {"Country": "Vietnam", "City": "Da Nang", "Total cases": "6", "Current cases": "6", "Recovered": "0", "Deceased": "0"}, "bbox": [106.6961966, 20.8611316, 106.7149603, 20.8613991], "geometry": {"type": "Point", "coordinates": [106.7055837, 20.8612633]}}, {"type": "Feature", "properties": {"Country": "Vietnam", "City": "Da Nang", "Total cases": "6", "Current cases": "6", "Recovered": "0", "Deceased": "0"}, "bbox": [106.7149603, 20.8610435, 106.7221402, 20.8611316], "geometry": {"type": "Point", "coordinates": [106.7184711, 20.8610435]}}]}