{"type": "FeatureCollection", "licence": "Data \u00a9 OpenStreetMap contributors, ODbL 1.0. https://osm.org/copyright", "features": [{"type": "Feature", "properties": {"Country": "Vietnam", "City": "Ha Tinh", "Total cases": "1", "Current cases": "1", "Recovered": "0", "Deceased": "0"}, "bbox": [105.1034678, 17.9096017, 106.7527613, 19.0065152], "geometry": {"type": "Point", "coordinates": [105.7842774, 18.2879059]}}, {"type": "Feature", "properties": {"Country": "Vietnam", "City": "Ha Tinh", "Total cases": "1", "Current cases": "1", "Recovered": "0", "Deceased": "0"}, "bbox": [105.7419482, 18.1852745, 106.0619482, 18.5052745], "geometry": {"type": "Point", "coordinates": [105.9019482, 18.3452745]}}, {"type": "Feature", "properties": {"Country": "Vietnam", "City": "Ha Tinh", "Total cases": "1", "Current cases": "1", "Recovered": "0", "Deceased": "0"}, "bbox": [105.8599995, 18.308026, 105.9433405, 18.400809], "geometry": {"type": "Point", "coordinates": [105.89768299184878, 18.3543859]}}]}