{"type": "FeatureCollection", "licence": "Data \u00a9 OpenStreetMap contributors, ODbL 1.0. https://osm.org/copyright", "features": [{"type": "Feature", "properties": {"Country": "Vietnam", "City": "Hai Duong", "Total cases": "1", "Current cases": "1", "Recovered": "0", "Deceased": "0"}, "bbox": [106.1243692, 20.684379, 106.6116443, 21.2369932], "geometry": {"type": "Point", "coordinates": [106.3780373, 20.9443681]}}]}