{"type": "FeatureCollection", "licence": "Data \u00a9 OpenStreetMap contributors, ODbL 1.0. https://osm.org/copyright", "features": [{"type": "Feature", "properties": {"Country": "Vietnam", "City": "Ho Chi Minh City", "Total cases": "40", "Current cases": "37", "Recovered": "3", "Deceased": "0"}, "bbox": [106.3567159, 10.1399458, 107.0276712, 11.1595357], "geometry": {"type": "Point", "coordinates": [106.76197937344351, 10.6497452]}}, {"type": "Feature", "properties": {"Country": "Vietnam", "City": "Ho Chi Minh City", "Total cases": "40", "Current cases": "37", "Recovered": "3", "Deceased": "0"}, "bbox": [106.5417555, 10.6158439, 106.8617555, 10.9358439], "geometry": {"type": "Point", "coordinates": [106.7017555, 10.7758439]}}, {"type": "Feature", "properties": {"Country": "Vietnam", "City": "Ho Chi Minh City", "Total cases": "40", "Current cases": "37", "Recovered": "3", "Deceased": "0"}, "bbox": [106.6660659, 10.7472932, 106.6661659, 10.7473932], "geometry": {"type": "Point", "coordinates": [106.6661159, 10.7473432]}}]}