{"type": "FeatureCollection", "licence": "Data \u00a9 OpenStreetMap contributors, ODbL 1.0. https://osm.org/copyright", "features": [{"type": "Feature", "properties": {"Country": "Vietnam", "City": "Khanh Hoa", "Total cases": "1", "Current cases": "0", "Recovered": "1", "Deceased": "0"}, "bbox": [108.6710126, 7.8911481, 114.3364815, 12.8685237], "geometry": {"type": "Point", "coordinates": [108.9950386, 12.1960803]}}, {"type": "Feature", "properties": {"Country": "Vietnam", "City": "Khanh Hoa", "Total cases": "1", "Current cases": "0", "Recovered": "1", "Deceased": "0"}, "bbox": [105.1703092, 10.6564725, 105.2103092, 10.6964725], "geometry": {"type": "Point", "coordinates": [105.1903092, 10.6764725]}}, {"type": "Feature", "properties": {"Country": "Vietnam", "City": "Khanh Hoa", "Total cases": "1", "Current cases": "0", "Recovered": "1", "Deceased": "0"}, "bbox": [105.9878954, 9.3740245, 106.0278954, 9.4140245], "geometry": {"type": "Point", "coordinates": [106.0078954, 9.3940245]}}, {"type": "Feature", "properties": {"Country": "Vietnam", "City": "Khanh Hoa", "Total cases": "1", "Current cases": "0", "Recovered": "1", "Deceased": "0"}, "bbox": [105.590174, 18.250423, 105.630174, 18.290423], "geometry": {"type": "Point", "coordinates": [105.610174, 18.270423]}}, {"type": "Feature", "properties": {"Country": "Vietnam", "City": "Khanh Hoa", "Total cases": "1", "Current cases": "0", "Recovered": "1", "Deceased": "0"}, "bbox": [106.1385427, 9.3696483, 106.1785427, 9.4096483], "geometry": {"type": "Point", "coordinates": [106.1585427, 9.3896483]}}]}