{"type": "FeatureCollection", "licence": "Data \u00a9 OpenStreetMap contributors, ODbL 1.0. https://osm.org/copyright", "features": [{"type": "Feature", "properties": {"Country": "Vietnam", "City": "Ninh Thuan", "Total cases": "2", "Current cases": "2", "Recovered": "0", "Deceased": "0"}, "bbox": [108.5516623, 10.7630844, 109.5373734, 12.1645338], "geometry": {"type": "Point", "coordinates": [108.8983408, 11.7449715]}}, {"type": "Feature", "properties": {"Country": "Vietnam", "City": "Ninh Thuan", "Total cases": "2", "Current cases": "2", "Recovered": "0", "Deceased": "0"}, "bbox": [106.1442143, 11.3082995, 106.1443143, 11.3083995], "geometry": {"type": "Point", "coordinates": [106.1442643, 11.3083495]}}]}