{"type": "FeatureCollection", "licence": "Data \u00a9 OpenStreetMap contributors, ODbL 1.0. https://osm.org/copyright", "features": [{"type": "Feature", "properties": {"Country": "Vietnam", "City": "Quang Nam", "Total cases": "3", "Current cases": "3", "Recovered": "0", "Deceased": "0"}, "bbox": [108.4305603, 11.9536573, 108.4306603, 11.9537573], "geometry": {"type": "Point", "coordinates": [108.4306103, 11.9537073]}}]}