{"type": "FeatureCollection", "licence": "Data \u00a9 OpenStreetMap contributors, ODbL 1.0. https://osm.org/copyright", "features": [{"type": "Feature", "properties": {"Country": "South Korea", "City": "Gyeongnam", "Total cases": "90", "Current cases": "90", "Recovered": "0", "Deceased": "0"}, "bbox": [127.5758886, 34.1697419, 129.2193882, 35.9102216], "geometry": {"type": "Point", "coordinates": [128.6925, 35.2382]}}, {"type": "Feature", "properties": {"Country": "South Korea", "City": "Gyeongnam", "Total cases": "90", "Current cases": "90", "Recovered": "0", "Deceased": "0"}, "bbox": [127.9068062, 35.6875343, 127.9069062, 35.6876343], "geometry": {"type": "Point", "coordinates": [127.9068562, 35.6875843]}}]}