{"type": "FeatureCollection", "licence": "Data \u00a9 OpenStreetMap contributors, ODbL 1.0. https://osm.org/copyright", "features": [{"type": "Feature", "properties": {"Country": "Philippines", "City": "Batanes", "Total cases": "0", "Current cases": "0", "Recovered": "0", "Deceased": "0"}, "bbox": [119.3339456, 18.0842465, 124.4539456, 23.2042465], "geometry": {"type": "Point", "coordinates": [121.8939456, 20.6442465]}}, {"type": "Feature", "properties": {"Country": "Philippines", "City": "Batanes", "Total cases": "0", "Current cases": "0", "Recovered": "0", "Deceased": "0"}, "bbox": [121.6316611, 19.8177402, 122.3020133, 21.2594616], "geometry": {"type": "Point", "coordinates": [121.86086909678635, 20.6902185]}}, {"type": "Feature", "properties": {"Country": "Philippines", "City": "Batanes", "Total cases": "0", "Current cases": "0", "Recovered": "0", "Deceased": "0"}, "bbox": [121.0032621, 14.6125003, 121.0069471, 14.6141857], "geometry": {"type": "Point", "coordinates": [121.0049891, 14.6130413]}}, {"type": "Feature", "properties": {"Country": "Philippines", "City": "Batanes", "Total cases": "0", "Current cases": "0", "Recovered": "0", "Deceased": "0"}, "bbox": [121.0069471, 14.6107292, 121.0092987, 14.6125167], "geometry": {"type": "Point", "coordinates": [121.0081555, 14.6115826]}}, {"type": "Feature", "properties": {"Country": "Philippines", "City": "Batanes", "Total cases": "0", "Current cases": "0", "Recovered": "0", "Deceased": "0"}, "bbox": [121.0092987, 14.6098411, 121.0104299, 14.6107292], "geometry": {"type": "Point", "coordinates": [121.0104299, 14.6098411]}}]}