{"type": "FeatureCollection", "licence": "Data \u00a9 OpenStreetMap contributors, ODbL 1.0. https://osm.org/copyright", "features": [{"type": "Feature", "properties": {"Country": "Philippines", "City": "Cainta", "Total cases": "0", "Current cases": "-1", "Recovered": "0", "Deceased": "1"}, "bbox": [121.0753885, 14.5400019, 121.1553885, 14.6200019], "geometry": {"type": "Point", "coordinates": [121.1153885, 14.5800019]}}, {"type": "Feature", "properties": {"Country": "Philippines", "City": "Cainta", "Total cases": "0", "Current cases": "-1", "Recovered": "0", "Deceased": "1"}, "bbox": [121.0946307, 14.547912, 121.1450774, 14.6365115], "geometry": {"type": "Point", "coordinates": [121.12351813800596, 14.592419]}}, {"type": "Feature", "properties": {"Country": "Philippines", "City": "Cainta", "Total cases": "0", "Current cases": "-1", "Recovered": "0", "Deceased": "1"}, "bbox": [120.9742924, 14.6379899, 120.9745728, 14.6396135], "geometry": {"type": "Point", "coordinates": [120.9744363, 14.6387388]}}]}