{"type": "FeatureCollection", "licence": "Data \u00a9 OpenStreetMap contributors, ODbL 1.0. https://osm.org/copyright", "features": [{"type": "Feature", "properties": {"Country": "Philippines", "City": "Camarines Sur", "Total cases": "1", "Current cases": "1", "Recovered": "0", "Deceased": "0"}, "bbox": [120.7665172, 11.106175, 125.8865172, 16.226175], "geometry": {"type": "Point", "coordinates": [123.3265172, 13.666175]}}, {"type": "Feature", "properties": {"Country": "Philippines", "City": "Camarines Sur", "Total cases": "1", "Current cases": "1", "Recovered": "0", "Deceased": "0"}, "bbox": [122.5286235, 13.187483, 124.0586451, 14.2666856], "geometry": {"type": "Point", "coordinates": [123.32885895465554, 13.7271157]}}]}