{"type": "FeatureCollection", "licence": "Data \u00a9 OpenStreetMap contributors, ODbL 1.0. https://osm.org/copyright", "features": [{"type": "Feature", "properties": {"Country": "Philippines", "City": "La Union", "Total cases": "0", "Current cases": "0", "Recovered": "0", "Deceased": "0"}, "bbox": [117.8489899, 14.0135957, 122.9689899, 19.1335957], "geometry": {"type": "Point", "coordinates": [120.4089899, 16.5735957]}}, {"type": "Feature", "properties": {"Country": "Philippines", "City": "La Union", "Total cases": "0", "Current cases": "0", "Recovered": "0", "Deceased": "0"}, "bbox": [120.1364554, 16.176663, 120.585139, 16.9778287], "geometry": {"type": "Point", "coordinates": [120.33564640358611, 16.579342150000002]}}, {"type": "Feature", "properties": {"Country": "Philippines", "City": "La Union", "Total cases": "0", "Current cases": "0", "Recovered": "0", "Deceased": "0"}, "bbox": [121.9418124, 11.9122706, 121.9818124, 11.9522706], "geometry": {"type": "Point", "coordinates": [121.9618124, 11.9322706]}}, {"type": "Feature", "properties": {"Country": "Philippines", "City": "La Union", "Total cases": "0", "Current cases": "0", "Recovered": "0", "Deceased": "0"}, "bbox": [121.944444, 11.906111, 121.984444, 11.946111], "geometry": {"type": "Point", "coordinates": [121.964444, 11.926111]}}, {"type": "Feature", "properties": {"Country": "Philippines", "City": "La Union", "Total cases": "0", "Current cases": "0", "Recovered": "0", "Deceased": "0"}, "bbox": [124.4483328, 9.8323372, 124.4883328, 9.8723372], "geometry": {"type": "Point", "coordinates": [124.4683328, 9.8523372]}}, {"type": "Feature", "properties": {"Country": "Philippines", "City": "La Union", "Total cases": "0", "Current cases": "0", "Recovered": "0", "Deceased": "0"}, "bbox": [125.2265011, 6.6670378, 125.2665011, 6.7070378], "geometry": {"type": "Point", "coordinates": [125.2465011, 6.6870378]}}, {"type": "Feature", "properties": {"Country": "Philippines", "City": "La Union", "Total cases": "0", "Current cases": "0", "Recovered": "0", "Deceased": "0"}, "bbox": [125.517864, 9.0638433, 125.557864, 9.1038433], "geometry": {"type": "Point", "coordinates": [125.537864, 9.0838433]}}, {"type": "Feature", "properties": {"Country": "Philippines", "City": "La Union", "Total cases": "0", "Current cases": "0", "Recovered": "0", "Deceased": "0"}, "bbox": [126.0733458, 6.6810066, 126.1133458, 6.7210066], "geometry": {"type": "Point", "coordinates": [126.0933458, 6.7010066]}}, {"type": "Feature", "properties": {"Country": "Philippines", "City": "La Union", "Total cases": "0", "Current cases": "0", "Recovered": "0", "Deceased": "0"}, "bbox": [124.974873, 10.8412316, 125.014873, 10.8812316], "geometry": {"type": "Point", "coordinates": [124.994873, 10.8612316]}}, {"type": "Feature", "properties": {"Country": "Philippines", "City": "La Union", "Total cases": "0", "Current cases": "0", "Recovered": "0", "Deceased": "0"}, "bbox": [124.3051602, 10.6494953, 124.3451602, 10.6894953], "geometry": {"type": "Point", "coordinates": [124.3251602, 10.6694953]}}]}