{"type": "FeatureCollection", "licence": "Data \u00a9 OpenStreetMap contributors, ODbL 1.0. https://osm.org/copyright", "features": [{"type": "Feature", "properties": {"Country": "Philippines", "City": "Malabon", "Total cases": "0", "Current cases": "0", "Recovered": "0", "Deceased": "0"}, "bbox": [120.9209997, 14.6450559, 121.0002301, 14.7044133], "geometry": {"type": "Point", "coordinates": [120.95810516453403, 14.6747254]}}, {"type": "Feature", "properties": {"Country": "Philippines", "City": "Malabon", "Total cases": "0", "Current cases": "0", "Recovered": "0", "Deceased": "0"}, "bbox": [120.7973542, 14.515233, 121.1173542, 14.835233], "geometry": {"type": "Point", "coordinates": [120.9573542, 14.675233]}}, {"type": "Feature", "properties": {"Country": "Philippines", "City": "Malabon", "Total cases": "0", "Current cases": "0", "Recovered": "0", "Deceased": "0"}, "bbox": [120.9827947, 14.6154794, 120.9846526, 14.6156048], "geometry": {"type": "Point", "coordinates": [120.9836831, 14.6155535]}}, {"type": "Feature", "properties": {"Country": "Philippines", "City": "Malabon", "Total cases": "0", "Current cases": "0", "Recovered": "0", "Deceased": "0"}, "bbox": [120.9846526, 14.6153351, 120.9865402, 14.6154794], "geometry": {"type": "Point", "coordinates": [120.9854412, 14.6154191]}}, {"type": "Feature", "properties": {"Country": "Philippines", "City": "Malabon", "Total cases": "0", "Current cases": "0", "Recovered": "0", "Deceased": "0"}, "bbox": [121.1157943, 14.5667868, 121.1160716, 14.5671874], "geometry": {"type": "Point", "coordinates": [121.115944, 14.5669539]}}]}