{"type": "FeatureCollection", "licence": "Data \u00a9 OpenStreetMap contributors, ODbL 1.0. https://osm.org/copyright", "features": [{"type": "Feature", "properties": {"Country": "Philippines", "City": "Para\u00f1aque", "Total cases": "8", "Current cases": "8", "Recovered": "0", "Deceased": "0"}, "bbox": [120.9717467, 14.4342173, 121.0479201, 14.5332374], "geometry": {"type": "Point", "coordinates": [120.9915488, 14.5007016]}}, {"type": "Feature", "properties": {"Country": "Philippines", "City": "Para\u00f1aque", "Total cases": "8", "Current cases": "8", "Recovered": "0", "Deceased": "0"}, "bbox": [120.9741996, 14.4342173, 121.0479201, 14.5332374], "geometry": {"type": "Point", "coordinates": [121.01725876355343, 14.483733950000001]}}]}