{"type": "FeatureCollection", "licence": "Data \u00a9 OpenStreetMap contributors, ODbL 1.0. https://osm.org/copyright", "features": [{"type": "Feature", "properties": {"Country": "Philippines", "City": "Rizal", "Total cases": "12", "Current cases": "10", "Recovered": "0", "Deceased": "2"}, "bbox": [118.69, 12.09, 123.81, 17.21], "geometry": {"type": "Point", "coordinates": [121.25, 14.65]}}, {"type": "Feature", "properties": {"Country": "Philippines", "City": "Rizal", "Total cases": "12", "Current cases": "10", "Recovered": "0", "Deceased": "2"}, "bbox": [121.093081, 14.2869834, 121.4504429, 14.89595], "geometry": {"type": "Point", "coordinates": [121.27860984162479, 14.5917332]}}, {"type": "Feature", "properties": {"Country": "Philippines", "City": "Rizal", "Total cases": "12", "Current cases": "10", "Recovered": "0", "Deceased": "2"}, "bbox": [121.3704996, 14.0634042, 121.4309128, 14.1284897], "geometry": {"type": "Point", "coordinates": [121.40114801263798, 14.097672750000001]}}, {"type": "Feature", "properties": {"Country": "Philippines", "City": "Rizal", "Total cases": "12", "Current cases": "10", "Recovered": "0", "Deceased": "2"}, "bbox": [121.3541099, 14.0752723, 121.4341099, 14.1552723], "geometry": {"type": "Point", "coordinates": [121.3941099, 14.1152723]}}, {"type": "Feature", "properties": {"Country": "Philippines", "City": "Rizal", "Total cases": "12", "Current cases": "10", "Recovered": "0", "Deceased": "2"}, "bbox": [117.6013305, 8.9902572, 117.6813305, 9.0702572], "geometry": {"type": "Point", "coordinates": [117.6413305, 9.0302572]}}, {"type": "Feature", "properties": {"Country": "Philippines", "City": "Rizal", "Total cases": "12", "Current cases": "10", "Recovered": "0", "Deceased": "2"}, "bbox": [123.5098159, 8.4855415, 123.5898159, 8.5655415], "geometry": {"type": "Point", "coordinates": [123.5498159, 8.5255415]}}, {"type": "Feature", "properties": {"Country": "Philippines", "City": "Rizal", "Total cases": "12", "Current cases": "10", "Recovered": "0", "Deceased": "2"}, "bbox": [121.0650406, 15.6687764, 121.1450406, 15.7487764], "geometry": {"type": "Point", "coordinates": [121.1050406, 15.7087764]}}, {"type": "Feature", "properties": {"Country": "Philippines", "City": "Rizal", "Total cases": "12", "Current cases": "10", "Recovered": "0", "Deceased": "2"}, "bbox": [121.3058649, 17.8057845, 121.3858649, 17.8857845], "geometry": {"type": "Point", "coordinates": [121.3458649, 17.8457845]}}, {"type": "Feature", "properties": {"Country": "Philippines", "City": "Rizal", "Total cases": "12", "Current cases": "10", "Recovered": "0", "Deceased": "2"}, "bbox": [121.5556717, 17.4594886, 121.6356717, 17.5394886], "geometry": {"type": "Point", "coordinates": [121.5956717, 17.4994886]}}, {"type": "Feature", "properties": {"Country": "Philippines", "City": "Rizal", "Total cases": "12", "Current cases": "10", "Recovered": "0", "Deceased": "2"}, "bbox": [120.9238808, 12.4184969, 121.0038808, 12.4984969], "geometry": {"type": "Point", "coordinates": [120.9638808, 12.4584969]}}]}