{"type": "FeatureCollection", "licence": "Data \u00a9 OpenStreetMap contributors, ODbL 1.0. https://osm.org/copyright", "features": [{"type": "Feature", "properties": {"Country": "Philippines", "City": "Tagaytay", "Total cases": "0", "Current cases": "0", "Recovered": "0", "Deceased": "0"}, "bbox": [120.8035545, 13.9549812, 121.1235545, 14.2749812], "geometry": {"type": "Point", "coordinates": [120.9635545, 14.1149812]}}, {"type": "Feature", "properties": {"Country": "Philippines", "City": "Tagaytay", "Total cases": "0", "Current cases": "0", "Recovered": "0", "Deceased": "0"}, "bbox": [120.8859131, 14.0791106, 121.0514021, 14.1570904], "geometry": {"type": "Point", "coordinates": [120.95565824674506, 14.11614185]}}, {"type": "Feature", "properties": {"Country": "Philippines", "City": "Tagaytay", "Total cases": "0", "Current cases": "0", "Recovered": "0", "Deceased": "0"}, "bbox": [125.3164783, 7.2504394, 125.3564783, 7.2904394], "geometry": {"type": "Point", "coordinates": [125.3364783, 7.2704394]}}, {"type": "Feature", "properties": {"Country": "Philippines", "City": "Tagaytay", "Total cases": "0", "Current cases": "0", "Recovered": "0", "Deceased": "0"}, "bbox": [124.796667, 10.33, 124.836667, 10.37], "geometry": {"type": "Point", "coordinates": [124.816667, 10.35]}}, {"type": "Feature", "properties": {"Country": "Philippines", "City": "Tagaytay", "Total cases": "0", "Current cases": "0", "Recovered": "0", "Deceased": "0"}, "bbox": [123.613247, 13.1417715, 123.653247, 13.1817715], "geometry": {"type": "Point", "coordinates": [123.633247, 13.1617715]}}, {"type": "Feature", "properties": {"Country": "Philippines", "City": "Tagaytay", "Total cases": "0", "Current cases": "0", "Recovered": "0", "Deceased": "0"}, "bbox": [124.0829228, 12.9529717, 124.1229228, 12.9929717], "geometry": {"type": "Point", "coordinates": [124.1029228, 12.9729717]}}, {"type": "Feature", "properties": {"Country": "Philippines", "City": "Tagaytay", "Total cases": "0", "Current cases": "0", "Recovered": "0", "Deceased": "0"}, "bbox": [121.9225514, 10.4429415, 121.9625514, 10.4829415], "geometry": {"type": "Point", "coordinates": [121.9425514, 10.4629415]}}, {"type": "Feature", "properties": {"Country": "Philippines", "City": "Tagaytay", "Total cases": "0", "Current cases": "0", "Recovered": "0", "Deceased": "0"}, "bbox": [125.5071673, 7.3222284, 125.5471673, 7.3622284], "geometry": {"type": "Point", "coordinates": [125.5271673, 7.3422284]}}, {"type": "Feature", "properties": {"Country": "Philippines", "City": "Tagaytay", "Total cases": "0", "Current cases": "0", "Recovered": "0", "Deceased": "0"}, "bbox": [125.0705842, 6.7337716, 125.1105842, 6.7737716], "geometry": {"type": "Point", "coordinates": [125.0905842, 6.7537716]}}, {"type": "Feature", "properties": {"Country": "Philippines", "City": "Tagaytay", "Total cases": "0", "Current cases": "0", "Recovered": "0", "Deceased": "0"}, "bbox": [125.5556191, 7.0738341, 125.5560438, 7.0743657], "geometry": {"type": "Point", "coordinates": [125.5558867, 7.0741691]}}]}