{"type": "FeatureCollection", "licence": "Data \u00a9 OpenStreetMap contributors, ODbL 1.0. https://osm.org/copyright", "features": [{"type": "Feature", "properties": {"Country": "India", "City": "Andaman and Nicobar Islands", "Total cases": "1", "Current cases": "1", "Recovered": "0", "Deceased": "0"}, "bbox": [92.2042072, 6.756326, 94.2773214, 13.6753133], "geometry": {"type": "Point", "coordinates": [92.5771329, 10.2188344]}}]}