{"type": "FeatureCollection", "licence": "Data \u00a9 OpenStreetMap contributors, ODbL 1.0. https://osm.org/copyright", "features": [{"type": "Feature", "properties": {"Country": "India", "City": "Andhra Pradesh", "Total cases": "10", "Current cases": "9", "Recovered": "1", "Deceased": "0"}, "bbox": [76.7611312, 12.6227232, 84.7647411, 19.1663296], "geometry": {"type": "Point", "coordinates": [80.1863809, 15.9240905]}}]}