{"type": "FeatureCollection", "licence": "Data \u00a9 OpenStreetMap contributors, ODbL 1.0. https://osm.org/copyright", "features": [{"type": "Feature", "properties": {"Country": "India", "City": "Goa", "Total cases": "3", "Current cases": "3", "Recovered": "0", "Deceased": "0"}, "bbox": [73.6829504, 14.9002456, 74.3379234, 15.8007631], "geometry": {"type": "Point", "coordinates": [74.0855134, 15.3004543]}}, {"type": "Feature", "properties": {"Country": "India", "City": "Goa", "Total cases": "3", "Current cases": "3", "Recovered": "0", "Deceased": "0"}, "bbox": [73.7647809, 15.6204023, 73.7648809, 15.6205023], "geometry": {"type": "Point", "coordinates": [73.7648309, 15.6204523]}}, {"type": "Feature", "properties": {"Country": "India", "City": "Goa", "Total cases": "3", "Current cases": "3", "Recovered": "0", "Deceased": "0"}, "bbox": [78.4035547, 26.4630914, 78.4135547, 26.4730914], "geometry": {"type": "Point", "coordinates": [78.4085547, 26.4680914]}}]}