{"type": "FeatureCollection", "licence": "Data \u00a9 OpenStreetMap contributors, ODbL 1.0. https://osm.org/copyright", "features": [{"type": "Feature", "properties": {"Country": "India", "City": "Himachal Pradesh", "Total cases": "2", "Current cases": "1", "Recovered": "0", "Deceased": "1"}, "bbox": [75.5940055, 30.3771701, 79.0123843, 33.2556686], "geometry": {"type": "Point", "coordinates": [77.34932051968858, 31.81676015]}}, {"type": "Feature", "properties": {"Country": "India", "City": "Himachal Pradesh", "Total cases": "2", "Current cases": "1", "Recovered": "0", "Deceased": "1"}, "bbox": [74.6228462, 29.3692352, 79.7428462, 34.4892352], "geometry": {"type": "Point", "coordinates": [77.1828462, 31.9292352]}}]}