{"type": "FeatureCollection", "licence": "Data \u00a9 OpenStreetMap contributors, ODbL 1.0. https://osm.org/copyright", "features": [{"type": "Feature", "properties": {"Country": "India", "City": "Puducherry", "Total cases": "1", "Current cases": "1", "Recovered": "0", "Deceased": "0"}, "bbox": [79.6706447, 11.7740568, 79.9906447, 12.0940568], "geometry": {"type": "Point", "coordinates": [79.8306447, 11.9340568]}}, {"type": "Feature", "properties": {"Country": "India", "City": "Puducherry", "Total cases": "1", "Current cases": "1", "Recovered": "0", "Deceased": "0"}, "bbox": [75.528447, 10.827721, 82.3137136, 16.7617112], "geometry": {"type": "Point", "coordinates": [79.80694879844232, 10.91564885]}}, {"type": "Feature", "properties": {"Country": "India", "City": "Puducherry", "Total cases": "1", "Current cases": "1", "Recovered": "0", "Deceased": "0"}, "bbox": [79.8231565, 11.92003, 79.8331565, 11.93003], "geometry": {"type": "Point", "coordinates": [79.8281565, 11.92503]}}]}