{"type": "FeatureCollection", "licence": "Data \u00a9 OpenStreetMap contributors, ODbL 1.0. https://osm.org/copyright", "features": [{"type": "Feature", "properties": {"Country": "India", "City": "Telangana", "Total cases": "43", "Current cases": "42", "Recovered": "1", "Deceased": "0"}, "bbox": [77.236585, 15.8363457, 81.3219165, 19.9172962], "geometry": {"type": "Point", "coordinates": [79.1151663, 17.8495919]}}]}